debug_toolbar_alchemy/__init__.py
debug_toolbar_alchemy/explain.py
debug_toolbar_alchemy/panels/__init__.py
debug_toolbar_alchemy/panels/sql/__init__.py
debug_toolbar_alchemy/panels/sql/forms.py
debug_toolbar_alchemy/panels/sql/panel.py
debug_toolbar_alchemy/panels/sql/tracking.py
debug_toolbar_alchemy/panels/sql/utils.py
debug_toolbar_alchemy/panels/sql/views.py
debug_toolbar_alchemy/templates/debug_toolbar/panels/sql-alchemy.html
django_debug_toolbar_alchemy-0.1.5.dist-info/METADATA
django_debug_toolbar_alchemy-0.1.5.dist-info/RECORD
django_debug_toolbar_alchemy-0.1.5.dist-info/WHEEL
django_debug_toolbar_alchemy-0.1.5.dist-info/top_level.txt
