Metadata-Version: 2.1
Name: django-debug-toolbar-alchemy
Version: 0.1.5
Summary: Django Debug Toolbar panel for SQLAlchemy.
Home-page: https://github.com/miki725/django-debug-toolbar-alchemy
Author: Miroslav Shubernetskiy
Author-email: UNKNOWN
License: MIT
Keywords: django django-debug-toolbar sqlalchemy
Platform: UNKNOWN
Classifier: Intended Audience :: Developers
Classifier: Natural Language :: English
Classifier: License :: OSI Approved :: MIT License
Classifier: Programming Language :: Python
Classifier: Programming Language :: Python :: 2.7
Classifier: Programming Language :: Python :: 3
Classifier: Development Status :: 2 - Pre-Alpha
Requires-Dist: django
Requires-Dist: django-debug-toolbar (>=1.8)
Requires-Dist: jsonplus
Requires-Dist: six
Requires-Dist: sqlalchemy
Requires-Dist: setuptools
